specsim/__init__.py
specsim/_astropy_init.py
specsim/atmosphere.py
specsim/camera.py
specsim/config.py
specsim/conftest.py
specsim/fastfiberacceptance.py
specsim/fiberloss.py
specsim/fitgalsim.py
specsim/instrument.py
specsim/observation.py
specsim/quickfiberloss.py
specsim/quickspecsim.py
specsim/simulator.py
specsim/source.py
specsim/transform.py
specsim/version.py
specsim/data/README.rst
specsim/data/config/desi.yaml
specsim/data/config/test.yaml
specsim/data/test/test-galsim-fiber-acceptance.fits
specsim/data/test/test_extinction.ecsv
specsim/data/test/test_fiberloss.ecsv
specsim/data/test/test_psf.ecsv
specsim/data/test/test_sky.ecsv
specsim/data/test/test_solar.ecsv
specsim/data/test/test_source.ecsv
specsim/data/test/test_throughput.ecsv
specsim/extern/__init__.py
specsim/tests/__init__.py
specsim/tests/coveragerc
specsim/tests/setup_package.py
specsim/tests/test_atmosphere.py
specsim/tests/test_camera.py
specsim/tests/test_config.py
specsim/tests/test_fiberloss.py
specsim/tests/test_instrument.py
specsim/tests/test_observation.py
specsim/tests/test_quickspecsim.py
specsim/tests/test_simulator.py
specsim/tests/test_source.py
specsim/tests/test_transform.py
specsim/utils/__init__.py
specsim-0.17.dist-info/METADATA
specsim-0.17.dist-info/WHEEL
specsim-0.17.dist-info/entry_points.txt
specsim-0.17.dist-info/top_level.txt
specsim-0.17.dist-info/RECORD
