Metadata-Version: 2.1
Name: specsim
Version: 0.17
Summary: Quick simulations of fiber spectrograph response
Home-page: https://github.com/desihub/specsim
Author: Specsim Developers
Author-email: dkirkby@uci.edu
License: BSD
Requires-Dist: astropy
Requires-Dist: scipy
Requires-Dist: pyyaml
Requires-Dist: speclite
